{"data":{"response":{"day":1428,"daily":{"day":1428,"song":"RRAmalgamaniac","modifier":"","difficulties":[{"day":1428,"difficulty":"Easy","song":"RRAmalgamaniac","modifier":"","seed":"nRgMmkBXuk","leaderboard":"D01428"},{"day":1428,"difficulty":"Medium","song":"RRAmalgamaniac","modifier":"","seed":"kAKM5aplLx","leaderboard":"D01428"},{"day":1428,"difficulty":"Hard","song":"RRAmalgamaniac","modifier":"","seed":"XNX9IpZICb","leaderboard":"D01428"},{"day":1428,"difficulty":"Impossible","song":"RRAmalgamaniac","modifier":"","seed":"tuWW2ddV7p","leaderboard":"D01428"}]}},"success":true,"reasonCode":null},"status":200}