{
    "max_hits": -1,
    "name": "P_C_M_CD_RRMatron",
    "scores": [
        {
            "InputMults": [
                {
                    "goods": 0,
                    "greats": 0,
                    "misses": 86,
                    "mult": 1,
                    "oks": 0,
                    "perfects": 105
                },
                {
                    "goods": 0,
                    "greats": 0,
                    "misses": 0,
                    "mult": 2,
                    "oks": 0,
                    "perfects": 2
                }
            ],
            "average": 0.0013,
            "base_score": 78921,
            "cheated": true,
            "create_epoch": 1739030649855,
            "dnf": false,
            "fc": false,
            "holds_hit": 45,
            "input_ratings": [
                {
                    "InputRatingCountPairs": [
                        {
                            "InputRating": "Perfect",
                            "NumberOfInputs": 105
                        },
                        {
                            "InputRating": "Miss",
                            "NumberOfInputs": 86
                        }
                    ],
                    "MultiplierValue": 1
                },
                {
                    "InputRatingCountPairs": [
                        {
                            "InputRating": "Perfect",
                            "NumberOfInputs": 2
                        }
                    ],
                    "MultiplierValue": 2
                }
            ],
            "max_combo": 12,
            "pfc": false,
            "player_id": "f7a46238-88a7-46ef-a4b4-70281373abe9",
            "player_name": "kr\u00e6\u014bki",
            "score": 75572,
            "total_goods": 0,
            "total_greats": 0,
            "total_misses": 86,
            "total_oks": 0,
            "total_perfects": 107,
            "update_epoch": 1739030649855,
            "vibe_chains_hit": 0,
            "vibe_chains_missed": 4,
            "vibe_duration": 0,
            "vibe_times": [],
            "vibes": 0
        },
        {
            "InputMults": [
                {
                    "goods": 0,
                    "greats": 0,
                    "misses": 0,
                    "mult": 1,
                    "oks": 0,
                    "perfects": 10
                },
                {
                    "goods": 0,
                    "greats": 0,
                    "misses": 0,
                    "mult": 2,
                    "oks": 0,
                    "perfects": 10
                },
                {
                    "goods": 0,
                    "greats": 0,
                    "misses": 0,
                    "mult": 3,
                    "oks": 0,
                    "perfects": 10
                },
                {
                    "goods": 0,
                    "greats": 0,
                    "misses": 0,
                    "mult": 4,
                    "oks": 0,
                    "perfects": 115
                },
                {
                    "goods": 0,
                    "greats": 0,
                    "misses": 1,
                    "mult": 8,
                    "oks": 0,
                    "perfects": 25
                }
            ],
            "average": -0.0016,
            "base_score": 58941,
            "cheated": false,
            "create_epoch": 1765271216268,
            "dnf": true,
            "fc": false,
            "holds_hit": 65,
            "input_ratings": [
                {
                    "InputRatingCountPairs": [
                        {
                            "InputRating": "Perfect",
                            "NumberOfInputs": 10
                        }
                    ],
                    "MultiplierValue": 1
                },
                {
                    "InputRatingCountPairs": [
                        {
                            "InputRating": "Perfect",
                            "NumberOfInputs": 10
                        }
                    ],
                    "MultiplierValue": 2
                },
                {
                    "InputRatingCountPairs": [
                        {
                            "InputRating": "Perfect",
                            "NumberOfInputs": 10
                        }
                    ],
                    "MultiplierValue": 3
                },
                {
                    "InputRatingCountPairs": [
                        {
                            "InputRating": "Perfect",
                            "NumberOfInputs": 115
                        }
                    ],
                    "MultiplierValue": 4
                },
                {
                    "InputRatingCountPairs": [
                        {
                            "InputRating": "Perfect",
                            "NumberOfInputs": 25
                        },
                        {
                            "InputRating": "Miss",
                            "NumberOfInputs": 1
                        }
                    ],
                    "MultiplierValue": 8
                }
            ],
            "max_combo": 170,
            "pfc": false,
            "player_id": "a0232d9c-4ebd-4f33-a960-753aedcfc871",
            "player_name": "Tyrantin",
            "score": 42141,
            "total_goods": 0,
            "total_greats": 0,
            "total_misses": 1,
            "total_oks": 0,
            "total_perfects": 170,
            "update_epoch": 1765271540873,
            "vibe_chains_hit": 3,
            "vibe_chains_missed": 0,
            "vibe_duration": 12.0593,
            "vibe_times": [
                80.4013,
                144.6684,
                209.5816
            ],
            "vibes": 3
        },
        {
            "InputMults": [
                {
                    "goods": 0,
                    "greats": 0,
                    "misses": 0,
                    "mult": 1,
                    "oks": 0,
                    "perfects": 10
                },
                {
                    "goods": 0,
                    "greats": 0,
                    "misses": 0,
                    "mult": 2,
                    "oks": 0,
                    "perfects": 10
                },
                {
                    "goods": 0,
                    "greats": 0,
                    "misses": 0,
                    "mult": 3,
                    "oks": 0,
                    "perfects": 10
                },
                {
                    "goods": 0,
                    "greats": 0,
                    "misses": 1,
                    "mult": 4,
                    "oks": 0,
                    "perfects": 59
                },
                {
                    "goods": 0,
                    "greats": 0,
                    "misses": 0,
                    "mult": 8,
                    "oks": 0,
                    "perfects": 17
                }
            ],
            "average": -0.0032,
            "base_score": 36963,
            "cheated": false,
            "create_epoch": 1739325732706,
            "dnf": true,
            "fc": false,
            "holds_hit": 25,
            "input_ratings": [
                {
                    "InputRatingCountPairs": [
                        {
                            "InputRating": "Perfect",
                            "NumberOfInputs": 10
                        }
                    ],
                    "MultiplierValue": 1
                },
                {
                    "InputRatingCountPairs": [
                        {
                            "InputRating": "Perfect",
                            "NumberOfInputs": 10
                        }
                    ],
                    "MultiplierValue": 2
                },
                {
                    "InputRatingCountPairs": [
                        {
                            "InputRating": "Perfect",
                            "NumberOfInputs": 10
                        }
                    ],
                    "MultiplierValue": 3
                },
                {
                    "InputRatingCountPairs": [
                        {
                            "InputRating": "Perfect",
                            "NumberOfInputs": 59
                        },
                        {
                            "InputRating": "Miss",
                            "NumberOfInputs": 1
                        }
                    ],
                    "MultiplierValue": 4
                },
                {
                    "InputRatingCountPairs": [
                        {
                            "InputRating": "Perfect",
                            "NumberOfInputs": 17
                        }
                    ],
                    "MultiplierValue": 8
                }
            ],
            "max_combo": 106,
            "pfc": false,
            "player_id": "fd886a41-12db-466e-a3b2-8ae93b0079a7",
            "player_name": "ksj64381",
            "score": 24820,
            "total_goods": 0,
            "total_greats": 0,
            "total_misses": 1,
            "total_oks": 0,
            "total_perfects": 106,
            "update_epoch": 1739326656556,
            "vibe_chains_hit": 1,
            "vibe_chains_missed": 1,
            "vibe_duration": 5.1973,
            "vibe_times": [
                100.9895
            ],
            "vibes": 1
        },
        {
            "InputMults": [
                {
                    "goods": 0,
                    "greats": 0,
                    "misses": 0,
                    "mult": 1,
                    "oks": 0,
                    "perfects": 10
                },
                {
                    "goods": 0,
                    "greats": 0,
                    "misses": 0,
                    "mult": 2,
                    "oks": 0,
                    "perfects": 10
                },
                {
                    "goods": 0,
                    "greats": 0,
                    "misses": 0,
                    "mult": 3,
                    "oks": 0,
                    "perfects": 10
                },
                {
                    "goods": 0,
                    "greats": 0,
                    "misses": 1,
                    "mult": 4,
                    "oks": 0,
                    "perfects": 15
                },
                {
                    "goods": 0,
                    "greats": 0,
                    "misses": 0,
                    "mult": 8,
                    "oks": 0,
                    "perfects": 6
                }
            ],
            "average": -0.0016,
            "base_score": 21645,
            "cheated": false,
            "create_epoch": 1742832097496,
            "dnf": true,
            "fc": false,
            "holds_hit": 9,
            "input_ratings": [
                {
                    "InputRatingCountPairs": [
                        {
                            "InputRating": "Perfect",
                            "NumberOfInputs": 10
                        }
                    ],
                    "MultiplierValue": 1
                },
                {
                    "InputRatingCountPairs": [
                        {
                            "InputRating": "Perfect",
                            "NumberOfInputs": 10
                        }
                    ],
                    "MultiplierValue": 2
                },
                {
                    "InputRatingCountPairs": [
                        {
                            "InputRating": "Perfect",
                            "NumberOfInputs": 10
                        }
                    ],
                    "MultiplierValue": 3
                },
                {
                    "InputRatingCountPairs": [
                        {
                            "InputRating": "Perfect",
                            "NumberOfInputs": 15
                        },
                        {
                            "InputRating": "Miss",
                            "NumberOfInputs": 1
                        }
                    ],
                    "MultiplierValue": 4
                },
                {
                    "InputRatingCountPairs": [
                        {
                            "InputRating": "Perfect",
                            "NumberOfInputs": 6
                        }
                    ],
                    "MultiplierValue": 8
                }
            ],
            "max_combo": 51,
            "pfc": false,
            "player_id": "f7741b7f-5159-4850-b029-6965b14c057f",
            "player_name": "Insane Freddy",
            "score": 9629,
            "total_goods": 0,
            "total_greats": 0,
            "total_misses": 1,
            "total_oks": 0,
            "total_perfects": 51,
            "update_epoch": 1742834123883,
            "vibe_chains_hit": 1,
            "vibe_chains_missed": 0,
            "vibe_duration": 5.1804,
            "vibe_times": [
                56.1744
            ],
            "vibes": 1
        },
        {
            "InputMults": [
                {
                    "goods": 0,
                    "greats": 0,
                    "misses": 0,
                    "mult": 1,
                    "oks": 0,
                    "perfects": 10
                },
                {
                    "goods": 0,
                    "greats": 0,
                    "misses": 0,
                    "mult": 2,
                    "oks": 0,
                    "perfects": 10
                },
                {
                    "goods": 0,
                    "greats": 0,
                    "misses": 0,
                    "mult": 3,
                    "oks": 0,
                    "perfects": 10
                },
                {
                    "goods": 0,
                    "greats": 0,
                    "misses": 1,
                    "mult": 4,
                    "oks": 0,
                    "perfects": 24
                }
            ],
            "average": -0.0025,
            "base_score": 21645,
            "cheated": false,
            "create_epoch": 1741639406790,
            "dnf": true,
            "fc": false,
            "holds_hit": 9,
            "input_ratings": [
                {
                    "InputRatingCountPairs": [
                        {
                            "InputRating": "Perfect",
                            "NumberOfInputs": 10
                        }
                    ],
                    "MultiplierValue": 1
                },
                {
                    "InputRatingCountPairs": [
                        {
                            "InputRating": "Perfect",
                            "NumberOfInputs": 10
                        }
                    ],
                    "MultiplierValue": 2
                },
                {
                    "InputRatingCountPairs": [
                        {
                            "InputRating": "Perfect",
                            "NumberOfInputs": 10
                        }
                    ],
                    "MultiplierValue": 3
                },
                {
                    "InputRatingCountPairs": [
                        {
                            "InputRating": "Perfect",
                            "NumberOfInputs": 24
                        },
                        {
                            "InputRating": "Miss",
                            "NumberOfInputs": 1
                        }
                    ],
                    "MultiplierValue": 4
                }
            ],
            "max_combo": 54,
            "pfc": false,
            "player_id": "228fabbe-5955-46f4-8a3a-9a8f1bc9ebed",
            "player_name": "Storch-CZ",
            "score": 8962,
            "total_goods": 0,
            "total_greats": 0,
            "total_misses": 1,
            "total_oks": 0,
            "total_perfects": 54,
            "update_epoch": 1741639648133,
            "vibe_chains_hit": 1,
            "vibe_chains_missed": 0,
            "vibe_duration": 0,
            "vibe_times": [],
            "vibes": 0
        },
        {
            "InputMults": [
                {
                    "goods": 0,
                    "greats": 0,
                    "misses": 0,
                    "mult": 1,
                    "oks": 0,
                    "perfects": 10
                },
                {
                    "goods": 0,
                    "greats": 0,
                    "misses": 0,
                    "mult": 2,
                    "oks": 0,
                    "perfects": 10
                },
                {
                    "goods": 0,
                    "greats": 0,
                    "misses": 0,
                    "mult": 3,
                    "oks": 0,
                    "perfects": 10
                },
                {
                    "goods": 0,
                    "greats": 0,
                    "misses": 1,
                    "mult": 4,
                    "oks": 0,
                    "perfects": 9
                }
            ],
            "average": 0.004,
            "base_score": 14652,
            "cheated": false,
            "create_epoch": 1741837771129,
            "dnf": true,
            "fc": false,
            "holds_hit": 3,
            "input_ratings": [
                {
                    "InputRatingCountPairs": [
                        {
                            "InputRating": "Perfect",
                            "NumberOfInputs": 10
                        }
                    ],
                    "MultiplierValue": 1
                },
                {
                    "InputRatingCountPairs": [
                        {
                            "InputRating": "Perfect",
                            "NumberOfInputs": 10
                        }
                    ],
                    "MultiplierValue": 2
                },
                {
                    "InputRatingCountPairs": [
                        {
                            "InputRating": "Perfect",
                            "NumberOfInputs": 10
                        }
                    ],
                    "MultiplierValue": 3
                },
                {
                    "InputRatingCountPairs": [
                        {
                            "InputRating": "Perfect",
                            "NumberOfInputs": 9
                        },
                        {
                            "InputRating": "Miss",
                            "NumberOfInputs": 1
                        }
                    ],
                    "MultiplierValue": 4
                }
            ],
            "max_combo": 39,
            "pfc": false,
            "player_id": "6b8bb167-17fa-4178-a02b-ab6291edb3b4",
            "player_name": "\u30aa\u30ea",
            "score": 5431,
            "total_goods": 0,
            "total_greats": 0,
            "total_misses": 1,
            "total_oks": 0,
            "total_perfects": 39,
            "update_epoch": 1741837870169,
            "vibe_chains_hit": 1,
            "vibe_chains_missed": 0,
            "vibe_duration": 0,
            "vibe_times": [],
            "vibes": 0
        },
        {
            "InputMults": [
                {
                    "goods": 0,
                    "greats": 0,
                    "misses": 0,
                    "mult": 1,
                    "oks": 0,
                    "perfects": 10
                },
                {
                    "goods": 0,
                    "greats": 0,
                    "misses": 0,
                    "mult": 2,
                    "oks": 0,
                    "perfects": 10
                },
                {
                    "goods": 0,
                    "greats": 0,
                    "misses": 1,
                    "mult": 3,
                    "oks": 0,
                    "perfects": 9
                }
            ],
            "average": -0.0058,
            "base_score": 12654,
            "cheated": false,
            "create_epoch": 1751743960494,
            "dnf": true,
            "fc": false,
            "holds_hit": 0,
            "input_ratings": [
                {
                    "InputRatingCountPairs": [
                        {
                            "InputRating": "Perfect",
                            "NumberOfInputs": 10
                        }
                    ],
                    "MultiplierValue": 1
                },
                {
                    "InputRatingCountPairs": [
                        {
                            "InputRating": "Perfect",
                            "NumberOfInputs": 10
                        }
                    ],
                    "MultiplierValue": 2
                },
                {
                    "InputRatingCountPairs": [
                        {
                            "InputRating": "Perfect",
                            "NumberOfInputs": 9
                        },
                        {
                            "InputRating": "Miss",
                            "NumberOfInputs": 1
                        }
                    ],
                    "MultiplierValue": 3
                }
            ],
            "max_combo": 29,
            "pfc": false,
            "player_id": "f4343dc8-5593-4096-b8e7-302060edb02c",
            "player_name": "Moshisme",
            "score": 3166,
            "total_goods": 0,
            "total_greats": 0,
            "total_misses": 1,
            "total_oks": 0,
            "total_perfects": 29,
            "update_epoch": 1751744520288,
            "vibe_chains_hit": 0,
            "vibe_chains_missed": 1,
            "vibe_duration": 0,
            "vibe_times": [],
            "vibes": 0
        },
        {
            "InputMults": [
                {
                    "goods": 0,
                    "greats": 0,
                    "misses": 0,
                    "mult": 1,
                    "oks": 0,
                    "perfects": 10
                },
                {
                    "goods": 0,
                    "greats": 0,
                    "misses": 1,
                    "mult": 2,
                    "oks": 0,
                    "perfects": 6
                }
            ],
            "average": 0.0016,
            "base_score": 8325,
            "cheated": false,
            "create_epoch": 1740541791867,
            "dnf": true,
            "fc": false,
            "holds_hit": 0,
            "input_ratings": [
                {
                    "InputRatingCountPairs": [
                        {
                            "InputRating": "Perfect",
                            "NumberOfInputs": 10
                        }
                    ],
                    "MultiplierValue": 1
                },
                {
                    "InputRatingCountPairs": [
                        {
                            "InputRating": "Perfect",
                            "NumberOfInputs": 6
                        },
                        {
                            "InputRating": "Miss",
                            "NumberOfInputs": 1
                        }
                    ],
                    "MultiplierValue": 2
                }
            ],
            "max_combo": 16,
            "pfc": false,
            "player_id": "df60a7ea-06de-40db-beff-559efcd5b7da",
            "player_name": "jesterwave",
            "score": 1222,
            "total_goods": 0,
            "total_greats": 0,
            "total_misses": 1,
            "total_oks": 0,
            "total_perfects": 16,
            "update_epoch": 1742703440657,
            "vibe_chains_hit": 0,
            "vibe_chains_missed": 0,
            "vibe_duration": 0,
            "vibe_times": [],
            "vibes": 0
        },
        {
            "InputMults": [
                {
                    "goods": 0,
                    "greats": 0,
                    "misses": 0,
                    "mult": 1,
                    "oks": 0,
                    "perfects": 10
                },
                {
                    "goods": 0,
                    "greats": 0,
                    "misses": 1,
                    "mult": 2,
                    "oks": 0,
                    "perfects": 5
                }
            ],
            "average": -0.0073,
            "base_score": 7992,
            "cheated": false,
            "create_epoch": 1744445493490,
            "dnf": true,
            "fc": false,
            "holds_hit": 0,
            "input_ratings": [
                {
                    "InputRatingCountPairs": [
                        {
                            "InputRating": "Perfect",
                            "NumberOfInputs": 10
                        }
                    ],
                    "MultiplierValue": 1
                },
                {
                    "InputRatingCountPairs": [
                        {
                            "InputRating": "Perfect",
                            "NumberOfInputs": 5
                        },
                        {
                            "InputRating": "Miss",
                            "NumberOfInputs": 1
                        }
                    ],
                    "MultiplierValue": 2
                }
            ],
            "max_combo": 15,
            "pfc": false,
            "player_id": "cbc1cc32-6998-4ba8-93dd-236614bb434d",
            "player_name": "Miku",
            "score": 1111,
            "total_goods": 0,
            "total_greats": 0,
            "total_misses": 1,
            "total_oks": 0,
            "total_perfects": 15,
            "update_epoch": 1744445516554,
            "vibe_chains_hit": 0,
            "vibe_chains_missed": 0,
            "vibe_duration": 0,
            "vibe_times": [],
            "vibes": 0
        },
        {
            "InputMults": [
                {
                    "goods": 0,
                    "greats": 0,
                    "misses": 0,
                    "mult": 1,
                    "oks": 0,
                    "perfects": 10
                },
                {
                    "goods": 0,
                    "greats": 0,
                    "misses": 1,
                    "mult": 2,
                    "oks": 0,
                    "perfects": 5
                }
            ],
            "average": -0.0123,
            "base_score": 7992,
            "cheated": false,
            "create_epoch": 1739112787080,
            "dnf": true,
            "fc": false,
            "holds_hit": 0,
            "input_ratings": [
                {
                    "InputRatingCountPairs": [
                        {
                            "InputRating": "Perfect",
                            "NumberOfInputs": 10
                        }
                    ],
                    "MultiplierValue": 1
                },
                {
                    "InputRatingCountPairs": [
                        {
                            "InputRating": "Perfect",
                            "NumberOfInputs": 5
                        },
                        {
                            "InputRating": "Miss",
                            "NumberOfInputs": 1
                        }
                    ],
                    "MultiplierValue": 2
                }
            ],
            "max_combo": 15,
            "pfc": false,
            "player_id": "c726fbf8-83f7-4228-b255-97174d4cc921",
            "player_name": "dpqbee",
            "score": 1110,
            "total_goods": 0,
            "total_greats": 0,
            "total_misses": 1,
            "total_oks": 0,
            "total_perfects": 15,
            "update_epoch": 1739112787080,
            "vibe_chains_hit": 0,
            "vibe_chains_missed": 0,
            "vibe_duration": 0,
            "vibe_times": [],
            "vibes": 0
        }
    ],
    "vibe_chains": -1
}