{
    "max_hits": -1,
    "name": "P_C_X_R_DLCOG04",
    "scores": [
        {
            "InputMults": [
                {
                    "goods": 0,
                    "greats": 0,
                    "misses": 0,
                    "mult": 1,
                    "oks": 0,
                    "perfects": 10
                },
                {
                    "goods": 0,
                    "greats": 0,
                    "misses": 0,
                    "mult": 2,
                    "oks": 0,
                    "perfects": 10
                },
                {
                    "goods": 0,
                    "greats": 0,
                    "misses": 0,
                    "mult": 3,
                    "oks": 0,
                    "perfects": 10
                },
                {
                    "goods": 0,
                    "greats": 2,
                    "misses": 0,
                    "mult": 4,
                    "oks": 0,
                    "perfects": 359
                },
                {
                    "goods": 0,
                    "greats": 0,
                    "misses": 0,
                    "mult": 8,
                    "oks": 0,
                    "perfects": 105
                }
            ],
            "average": -0.0056,
            "base_score": 165168,
            "cheated": false,
            "create_epoch": 1770315559284,
            "dnf": false,
            "fc": true,
            "holds_hit": 40,
            "input_ratings": [
                {
                    "InputRatingCountPairs": [
                        {
                            "InputRating": "Perfect",
                            "NumberOfInputs": 10
                        }
                    ],
                    "MultiplierValue": 1
                },
                {
                    "InputRatingCountPairs": [
                        {
                            "InputRating": "Perfect",
                            "NumberOfInputs": 10
                        }
                    ],
                    "MultiplierValue": 2
                },
                {
                    "InputRatingCountPairs": [
                        {
                            "InputRating": "Perfect",
                            "NumberOfInputs": 10
                        }
                    ],
                    "MultiplierValue": 3
                },
                {
                    "InputRatingCountPairs": [
                        {
                            "InputRating": "Perfect",
                            "NumberOfInputs": 359
                        },
                        {
                            "InputRating": "Great",
                            "NumberOfInputs": 2
                        }
                    ],
                    "MultiplierValue": 4
                },
                {
                    "InputRatingCountPairs": [
                        {
                            "InputRating": "Perfect",
                            "NumberOfInputs": 105
                        }
                    ],
                    "MultiplierValue": 8
                }
            ],
            "max_combo": 496,
            "pfc": false,
            "player_id": "1a96865b-53ff-4e82-b54a-275a79093e1d",
            "player_name": "imhinder",
            "score": 1312987,
            "total_goods": 0,
            "total_greats": 2,
            "total_misses": 0,
            "total_oks": 0,
            "total_perfects": 494,
            "update_epoch": 1770380940925,
            "vibe_chains_hit": 5,
            "vibe_chains_missed": 0,
            "vibe_duration": 24.7715,
            "vibe_times": [
                204.9009,
                298.8974,
                409.6034
            ],
            "vibes": 3
        },
        {
            "InputMults": [
                {
                    "goods": 0,
                    "greats": 0,
                    "misses": 0,
                    "mult": 1,
                    "oks": 0,
                    "perfects": 10
                },
                {
                    "goods": 0,
                    "greats": 0,
                    "misses": 0,
                    "mult": 2,
                    "oks": 0,
                    "perfects": 10
                },
                {
                    "goods": 0,
                    "greats": 0,
                    "misses": 0,
                    "mult": 3,
                    "oks": 0,
                    "perfects": 10
                },
                {
                    "goods": 0,
                    "greats": 0,
                    "misses": 0,
                    "mult": 4,
                    "oks": 0,
                    "perfects": 358
                },
                {
                    "goods": 0,
                    "greats": 0,
                    "misses": 0,
                    "mult": 8,
                    "oks": 0,
                    "perfects": 105
                }
            ],
            "average": -0.0022,
            "base_score": 164169,
            "cheated": false,
            "create_epoch": 1770342666120,
            "dnf": false,
            "fc": true,
            "holds_hit": 40,
            "input_ratings": [
                {
                    "InputRatingCountPairs": [
                        {
                            "InputRating": "Perfect",
                            "NumberOfInputs": 10
                        }
                    ],
                    "MultiplierValue": 1
                },
                {
                    "InputRatingCountPairs": [
                        {
                            "InputRating": "Perfect",
                            "NumberOfInputs": 10
                        }
                    ],
                    "MultiplierValue": 2
                },
                {
                    "InputRatingCountPairs": [
                        {
                            "InputRating": "Perfect",
                            "NumberOfInputs": 10
                        }
                    ],
                    "MultiplierValue": 3
                },
                {
                    "InputRatingCountPairs": [
                        {
                            "InputRating": "Perfect",
                            "NumberOfInputs": 358
                        }
                    ],
                    "MultiplierValue": 4
                },
                {
                    "InputRatingCountPairs": [
                        {
                            "InputRating": "Perfect",
                            "NumberOfInputs": 105
                        }
                    ],
                    "MultiplierValue": 8
                }
            ],
            "max_combo": 493,
            "pfc": true,
            "player_id": "d522f404-c4e7-44e9-b763-a791cbf95703",
            "player_name": "X.P.87",
            "score": 1308186,
            "total_goods": 0,
            "total_greats": 0,
            "total_misses": 0,
            "total_oks": 0,
            "total_perfects": 493,
            "update_epoch": 1770381505465,
            "vibe_chains_hit": 5,
            "vibe_chains_missed": 0,
            "vibe_duration": 24.7518,
            "vibe_times": [
                203.9416,
                298.7912,
                409.6512
            ],
            "vibes": 3
        },
        {
            "InputMults": [
                {
                    "goods": 0,
                    "greats": 0,
                    "misses": 0,
                    "mult": 1,
                    "oks": 0,
                    "perfects": 10
                },
                {
                    "goods": 0,
                    "greats": 0,
                    "misses": 0,
                    "mult": 2,
                    "oks": 0,
                    "perfects": 10
                },
                {
                    "goods": 0,
                    "greats": 0,
                    "misses": 0,
                    "mult": 3,
                    "oks": 0,
                    "perfects": 10
                },
                {
                    "goods": 0,
                    "greats": 1,
                    "misses": 0,
                    "mult": 4,
                    "oks": 0,
                    "perfects": 362
                },
                {
                    "goods": 0,
                    "greats": 0,
                    "misses": 0,
                    "mult": 8,
                    "oks": 0,
                    "perfects": 99
                }
            ],
            "average": -0.0074,
            "base_score": 163836,
            "cheated": false,
            "create_epoch": 1770346295330,
            "dnf": false,
            "fc": true,
            "holds_hit": 40,
            "input_ratings": [
                {
                    "InputRatingCountPairs": [
                        {
                            "InputRating": "Perfect",
                            "NumberOfInputs": 10
                        }
                    ],
                    "MultiplierValue": 1
                },
                {
                    "InputRatingCountPairs": [
                        {
                            "InputRating": "Perfect",
                            "NumberOfInputs": 10
                        }
                    ],
                    "MultiplierValue": 2
                },
                {
                    "InputRatingCountPairs": [
                        {
                            "InputRating": "Perfect",
                            "NumberOfInputs": 10
                        }
                    ],
                    "MultiplierValue": 3
                },
                {
                    "InputRatingCountPairs": [
                        {
                            "InputRating": "Perfect",
                            "NumberOfInputs": 362
                        },
                        {
                            "InputRating": "Great",
                            "NumberOfInputs": 1
                        }
                    ],
                    "MultiplierValue": 4
                },
                {
                    "InputRatingCountPairs": [
                        {
                            "InputRating": "Perfect",
                            "NumberOfInputs": 99
                        }
                    ],
                    "MultiplierValue": 8
                }
            ],
            "max_combo": 492,
            "pfc": false,
            "player_id": "c46a2167-5942-4e30-b08d-4cbbfb117ad1",
            "player_name": "Qco",
            "score": 1291642,
            "total_goods": 0,
            "total_greats": 1,
            "total_misses": 0,
            "total_oks": 0,
            "total_perfects": 491,
            "update_epoch": 1770346295330,
            "vibe_chains_hit": 5,
            "vibe_chains_missed": 0,
            "vibe_duration": 24.6323,
            "vibe_times": [
                203.0007,
                295.0405,
                409.9917
            ],
            "vibes": 3
        },
        {
            "InputMults": [
                {
                    "goods": 0,
                    "greats": 0,
                    "misses": 0,
                    "mult": 1,
                    "oks": 0,
                    "perfects": 10
                },
                {
                    "goods": 0,
                    "greats": 0,
                    "misses": 0,
                    "mult": 2,
                    "oks": 0,
                    "perfects": 10
                },
                {
                    "goods": 0,
                    "greats": 0,
                    "misses": 0,
                    "mult": 3,
                    "oks": 0,
                    "perfects": 10
                },
                {
                    "goods": 0,
                    "greats": 4,
                    "misses": 0,
                    "mult": 4,
                    "oks": 0,
                    "perfects": 353
                },
                {
                    "goods": 0,
                    "greats": 0,
                    "misses": 0,
                    "mult": 8,
                    "oks": 0,
                    "perfects": 102
                }
            ],
            "average": -0.002,
            "base_score": 162837,
            "cheated": false,
            "create_epoch": 1770382635178,
            "dnf": false,
            "fc": true,
            "holds_hit": 40,
            "input_ratings": [
                {
                    "InputRatingCountPairs": [
                        {
                            "InputRating": "Perfect",
                            "NumberOfInputs": 10
                        }
                    ],
                    "MultiplierValue": 1
                },
                {
                    "InputRatingCountPairs": [
                        {
                            "InputRating": "Perfect",
                            "NumberOfInputs": 10
                        }
                    ],
                    "MultiplierValue": 2
                },
                {
                    "InputRatingCountPairs": [
                        {
                            "InputRating": "Perfect",
                            "NumberOfInputs": 10
                        }
                    ],
                    "MultiplierValue": 3
                },
                {
                    "InputRatingCountPairs": [
                        {
                            "InputRating": "Perfect",
                            "NumberOfInputs": 353
                        },
                        {
                            "InputRating": "Great",
                            "NumberOfInputs": 4
                        }
                    ],
                    "MultiplierValue": 4
                },
                {
                    "InputRatingCountPairs": [
                        {
                            "InputRating": "Perfect",
                            "NumberOfInputs": 102
                        }
                    ],
                    "MultiplierValue": 8
                }
            ],
            "max_combo": 489,
            "pfc": false,
            "player_id": "7316f901-5e5e-4961-ae32-a83159bcd975",
            "player_name": "kolszk",
            "score": 1289016,
            "total_goods": 0,
            "total_greats": 4,
            "total_misses": 0,
            "total_oks": 0,
            "total_perfects": 485,
            "update_epoch": 1770382868989,
            "vibe_chains_hit": 5,
            "vibe_chains_missed": 0,
            "vibe_duration": 24.6464,
            "vibe_times": [
                122.9402,
                202.9576,
                292.8678,
                409.9972
            ],
            "vibes": 4
        },
        {
            "InputMults": [
                {
                    "goods": 0,
                    "greats": 0,
                    "misses": 0,
                    "mult": 1,
                    "oks": 0,
                    "perfects": 10
                },
                {
                    "goods": 0,
                    "greats": 0,
                    "misses": 0,
                    "mult": 2,
                    "oks": 0,
                    "perfects": 10
                },
                {
                    "goods": 0,
                    "greats": 0,
                    "misses": 0,
                    "mult": 3,
                    "oks": 0,
                    "perfects": 10
                },
                {
                    "goods": 0,
                    "greats": 1,
                    "misses": 0,
                    "mult": 4,
                    "oks": 0,
                    "perfects": 370
                },
                {
                    "goods": 0,
                    "greats": 2,
                    "misses": 0,
                    "mult": 8,
                    "oks": 0,
                    "perfects": 91
                }
            ],
            "average": 0.0012,
            "base_score": 164502,
            "cheated": false,
            "create_epoch": 1770336051722,
            "dnf": false,
            "fc": true,
            "holds_hit": 40,
            "input_ratings": [
                {
                    "InputRatingCountPairs": [
                        {
                            "InputRating": "Perfect",
                            "NumberOfInputs": 10
                        }
                    ],
                    "MultiplierValue": 1
                },
                {
                    "InputRatingCountPairs": [
                        {
                            "InputRating": "Perfect",
                            "NumberOfInputs": 10
                        }
                    ],
                    "MultiplierValue": 2
                },
                {
                    "InputRatingCountPairs": [
                        {
                            "InputRating": "Perfect",
                            "NumberOfInputs": 10
                        }
                    ],
                    "MultiplierValue": 3
                },
                {
                    "InputRatingCountPairs": [
                        {
                            "InputRating": "Perfect",
                            "NumberOfInputs": 370
                        },
                        {
                            "InputRating": "Great",
                            "NumberOfInputs": 1
                        }
                    ],
                    "MultiplierValue": 4
                },
                {
                    "InputRatingCountPairs": [
                        {
                            "InputRating": "Perfect",
                            "NumberOfInputs": 91
                        },
                        {
                            "InputRating": "Great",
                            "NumberOfInputs": 2
                        }
                    ],
                    "MultiplierValue": 8
                }
            ],
            "max_combo": 494,
            "pfc": false,
            "player_id": "81fa01b4-0b9d-414f-903d-e914705750e7",
            "player_name": "Liam",
            "score": 1279250,
            "total_goods": 0,
            "total_greats": 3,
            "total_misses": 0,
            "total_oks": 0,
            "total_perfects": 491,
            "update_epoch": 1770679994116,
            "vibe_chains_hit": 5,
            "vibe_chains_missed": 0,
            "vibe_duration": 25.1211,
            "vibe_times": [
                105.9438,
                202.8261,
                301.9296,
                385.5551
            ],
            "vibes": 4
        },
        {
            "InputMults": [
                {
                    "goods": 0,
                    "greats": 0,
                    "misses": 0,
                    "mult": 1,
                    "oks": 0,
                    "perfects": 10
                },
                {
                    "goods": 0,
                    "greats": 0,
                    "misses": 0,
                    "mult": 2,
                    "oks": 0,
                    "perfects": 10
                },
                {
                    "goods": 0,
                    "greats": 0,
                    "misses": 0,
                    "mult": 3,
                    "oks": 0,
                    "perfects": 10
                },
                {
                    "goods": 0,
                    "greats": 4,
                    "misses": 0,
                    "mult": 4,
                    "oks": 0,
                    "perfects": 371
                },
                {
                    "goods": 0,
                    "greats": 1,
                    "misses": 0,
                    "mult": 8,
                    "oks": 0,
                    "perfects": 88
                }
            ],
            "average": -0.0031,
            "base_score": 164502,
            "cheated": false,
            "create_epoch": 1770316888179,
            "dnf": false,
            "fc": true,
            "holds_hit": 40,
            "input_ratings": [
                {
                    "InputRatingCountPairs": [
                        {
                            "InputRating": "Perfect",
                            "NumberOfInputs": 10
                        }
                    ],
                    "MultiplierValue": 1
                },
                {
                    "InputRatingCountPairs": [
                        {
                            "InputRating": "Perfect",
                            "NumberOfInputs": 10
                        }
                    ],
                    "MultiplierValue": 2
                },
                {
                    "InputRatingCountPairs": [
                        {
                            "InputRating": "Perfect",
                            "NumberOfInputs": 10
                        }
                    ],
                    "MultiplierValue": 3
                },
                {
                    "InputRatingCountPairs": [
                        {
                            "InputRating": "Perfect",
                            "NumberOfInputs": 371
                        },
                        {
                            "InputRating": "Great",
                            "NumberOfInputs": 4
                        }
                    ],
                    "MultiplierValue": 4
                },
                {
                    "InputRatingCountPairs": [
                        {
                            "InputRating": "Perfect",
                            "NumberOfInputs": 88
                        },
                        {
                            "InputRating": "Great",
                            "NumberOfInputs": 1
                        }
                    ],
                    "MultiplierValue": 8
                }
            ],
            "max_combo": 494,
            "pfc": false,
            "player_id": "09f8ef53-657a-45de-a748-23f23ea9f78e",
            "player_name": "UltraCboy",
            "score": 1269456,
            "total_goods": 0,
            "total_greats": 5,
            "total_misses": 0,
            "total_oks": 0,
            "total_perfects": 489,
            "update_epoch": 1770320191851,
            "vibe_chains_hit": 5,
            "vibe_chains_missed": 0,
            "vibe_duration": 25.0564,
            "vibe_times": [
                101.0137,
                161.6451,
                293.0248,
                385.6979
            ],
            "vibes": 4
        },
        {
            "InputMults": [
                {
                    "goods": 0,
                    "greats": 0,
                    "misses": 0,
                    "mult": 1,
                    "oks": 0,
                    "perfects": 10
                },
                {
                    "goods": 0,
                    "greats": 0,
                    "misses": 0,
                    "mult": 2,
                    "oks": 0,
                    "perfects": 10
                },
                {
                    "goods": 0,
                    "greats": 0,
                    "misses": 0,
                    "mult": 3,
                    "oks": 0,
                    "perfects": 10
                },
                {
                    "goods": 1,
                    "greats": 4,
                    "misses": 0,
                    "mult": 4,
                    "oks": 0,
                    "perfects": 368
                },
                {
                    "goods": 0,
                    "greats": 6,
                    "misses": 0,
                    "mult": 8,
                    "oks": 0,
                    "perfects": 85
                }
            ],
            "average": -0.0008,
            "base_score": 164502,
            "cheated": false,
            "create_epoch": 1770324045701,
            "dnf": false,
            "fc": true,
            "holds_hit": 40,
            "input_ratings": [
                {
                    "InputRatingCountPairs": [
                        {
                            "InputRating": "Perfect",
                            "NumberOfInputs": 10
                        }
                    ],
                    "MultiplierValue": 1
                },
                {
                    "InputRatingCountPairs": [
                        {
                            "InputRating": "Perfect",
                            "NumberOfInputs": 10
                        }
                    ],
                    "MultiplierValue": 2
                },
                {
                    "InputRatingCountPairs": [
                        {
                            "InputRating": "Perfect",
                            "NumberOfInputs": 10
                        }
                    ],
                    "MultiplierValue": 3
                },
                {
                    "InputRatingCountPairs": [
                        {
                            "InputRating": "Perfect",
                            "NumberOfInputs": 368
                        },
                        {
                            "InputRating": "Great",
                            "NumberOfInputs": 4
                        },
                        {
                            "InputRating": "Good",
                            "NumberOfInputs": 1
                        }
                    ],
                    "MultiplierValue": 4
                },
                {
                    "InputRatingCountPairs": [
                        {
                            "InputRating": "Perfect",
                            "NumberOfInputs": 85
                        },
                        {
                            "InputRating": "Great",
                            "NumberOfInputs": 6
                        }
                    ],
                    "MultiplierValue": 8
                }
            ],
            "max_combo": 494,
            "pfc": false,
            "player_id": "944ca790-0734-4fc9-821d-872e7fb56726",
            "player_name": "MaxFusi0n12",
            "score": 1263649,
            "total_goods": 1,
            "total_greats": 10,
            "total_misses": 0,
            "total_oks": 0,
            "total_perfects": 483,
            "update_epoch": 1770389175572,
            "vibe_chains_hit": 5,
            "vibe_chains_missed": 0,
            "vibe_duration": 25.0638,
            "vibe_times": [
                100.7382,
                161.3754,
                288.4011,
                364.7982
            ],
            "vibes": 4
        },
        {
            "InputMults": [
                {
                    "goods": 0,
                    "greats": 0,
                    "misses": 0,
                    "mult": 1,
                    "oks": 0,
                    "perfects": 10
                },
                {
                    "goods": 0,
                    "greats": 0,
                    "misses": 0,
                    "mult": 2,
                    "oks": 0,
                    "perfects": 10
                },
                {
                    "goods": 0,
                    "greats": 0,
                    "misses": 0,
                    "mult": 3,
                    "oks": 0,
                    "perfects": 10
                },
                {
                    "goods": 2,
                    "greats": 11,
                    "misses": 0,
                    "mult": 4,
                    "oks": 0,
                    "perfects": 358
                },
                {
                    "goods": 0,
                    "greats": 2,
                    "misses": 0,
                    "mult": 8,
                    "oks": 0,
                    "perfects": 90
                }
            ],
            "average": 0.0025,
            "base_score": 164169,
            "cheated": false,
            "create_epoch": 1770339699247,
            "dnf": false,
            "fc": true,
            "holds_hit": 40,
            "input_ratings": [
                {
                    "InputRatingCountPairs": [
                        {
                            "InputRating": "Perfect",
                            "NumberOfInputs": 10
                        }
                    ],
                    "MultiplierValue": 1
                },
                {
                    "InputRatingCountPairs": [
                        {
                            "InputRating": "Perfect",
                            "NumberOfInputs": 10
                        }
                    ],
                    "MultiplierValue": 2
                },
                {
                    "InputRatingCountPairs": [
                        {
                            "InputRating": "Perfect",
                            "NumberOfInputs": 10
                        }
                    ],
                    "MultiplierValue": 3
                },
                {
                    "InputRatingCountPairs": [
                        {
                            "InputRating": "Perfect",
                            "NumberOfInputs": 358
                        },
                        {
                            "InputRating": "Great",
                            "NumberOfInputs": 11
                        },
                        {
                            "InputRating": "Good",
                            "NumberOfInputs": 2
                        }
                    ],
                    "MultiplierValue": 4
                },
                {
                    "InputRatingCountPairs": [
                        {
                            "InputRating": "Perfect",
                            "NumberOfInputs": 90
                        },
                        {
                            "InputRating": "Great",
                            "NumberOfInputs": 2
                        }
                    ],
                    "MultiplierValue": 8
                }
            ],
            "max_combo": 493,
            "pfc": false,
            "player_id": "6c8027a9-5ec1-4451-9d78-90f61a6c95f5",
            "player_name": "WhosKyle",
            "score": 1263252,
            "total_goods": 2,
            "total_greats": 13,
            "total_misses": 0,
            "total_oks": 0,
            "total_perfects": 478,
            "update_epoch": 1770339699247,
            "vibe_chains_hit": 5,
            "vibe_chains_missed": 0,
            "vibe_duration": 25.0947,
            "vibe_times": [
                107.8567,
                161.1404,
                292.8823,
                385.3005
            ],
            "vibes": 4
        },
        {
            "InputMults": [
                {
                    "goods": 0,
                    "greats": 0,
                    "misses": 0,
                    "mult": 1,
                    "oks": 0,
                    "perfects": 10
                },
                {
                    "goods": 0,
                    "greats": 1,
                    "misses": 0,
                    "mult": 2,
                    "oks": 0,
                    "perfects": 9
                },
                {
                    "goods": 0,
                    "greats": 0,
                    "misses": 0,
                    "mult": 3,
                    "oks": 0,
                    "perfects": 10
                },
                {
                    "goods": 0,
                    "greats": 4,
                    "misses": 0,
                    "mult": 4,
                    "oks": 0,
                    "perfects": 376
                },
                {
                    "goods": 0,
                    "greats": 0,
                    "misses": 0,
                    "mult": 8,
                    "oks": 0,
                    "perfects": 84
                }
            ],
            "average": 0.0022,
            "base_score": 164502,
            "cheated": false,
            "create_epoch": 1770315808662,
            "dnf": false,
            "fc": true,
            "holds_hit": 40,
            "input_ratings": [
                {
                    "InputRatingCountPairs": [
                        {
                            "InputRating": "Perfect",
                            "NumberOfInputs": 10
                        }
                    ],
                    "MultiplierValue": 1
                },
                {
                    "InputRatingCountPairs": [
                        {
                            "InputRating": "Perfect",
                            "NumberOfInputs": 9
                        },
                        {
                            "InputRating": "Great",
                            "NumberOfInputs": 1
                        }
                    ],
                    "MultiplierValue": 2
                },
                {
                    "InputRatingCountPairs": [
                        {
                            "InputRating": "Perfect",
                            "NumberOfInputs": 10
                        }
                    ],
                    "MultiplierValue": 3
                },
                {
                    "InputRatingCountPairs": [
                        {
                            "InputRating": "Perfect",
                            "NumberOfInputs": 376
                        },
                        {
                            "InputRating": "Great",
                            "NumberOfInputs": 4
                        }
                    ],
                    "MultiplierValue": 4
                },
                {
                    "InputRatingCountPairs": [
                        {
                            "InputRating": "Perfect",
                            "NumberOfInputs": 84
                        }
                    ],
                    "MultiplierValue": 8
                }
            ],
            "max_combo": 494,
            "pfc": false,
            "player_id": "ed59f0a3-002f-4c6e-96fa-184d2ad18a95",
            "player_name": "PataChu",
            "score": 1259732,
            "total_goods": 0,
            "total_greats": 5,
            "total_misses": 0,
            "total_oks": 0,
            "total_perfects": 489,
            "update_epoch": 1770315808662,
            "vibe_chains_hit": 5,
            "vibe_chains_missed": 0,
            "vibe_duration": 25.0735,
            "vibe_times": [
                101.004,
                161.531,
                233.9773,
                292.9998,
                385.4977
            ],
            "vibes": 5
        },
        {
            "InputMults": [
                {
                    "goods": 0,
                    "greats": 0,
                    "misses": 0,
                    "mult": 1,
                    "oks": 0,
                    "perfects": 10
                },
                {
                    "goods": 0,
                    "greats": 0,
                    "misses": 0,
                    "mult": 2,
                    "oks": 0,
                    "perfects": 10
                },
                {
                    "goods": 0,
                    "greats": 2,
                    "misses": 0,
                    "mult": 3,
                    "oks": 0,
                    "perfects": 8
                },
                {
                    "goods": 0,
                    "greats": 4,
                    "misses": 0,
                    "mult": 4,
                    "oks": 0,
                    "perfects": 366
                },
                {
                    "goods": 0,
                    "greats": 0,
                    "misses": 0,
                    "mult": 8,
                    "oks": 0,
                    "perfects": 89
                }
            ],
            "average": -0.0044,
            "base_score": 162837,
            "cheated": false,
            "create_epoch": 1770315878274,
            "dnf": false,
            "fc": true,
            "holds_hit": 40,
            "input_ratings": [
                {
                    "InputRatingCountPairs": [
                        {
                            "InputRating": "Perfect",
                            "NumberOfInputs": 10
                        }
                    ],
                    "MultiplierValue": 1
                },
                {
                    "InputRatingCountPairs": [
                        {
                            "InputRating": "Perfect",
                            "NumberOfInputs": 10
                        }
                    ],
                    "MultiplierValue": 2
                },
                {
                    "InputRatingCountPairs": [
                        {
                            "InputRating": "Perfect",
                            "NumberOfInputs": 8
                        },
                        {
                            "InputRating": "Great",
                            "NumberOfInputs": 2
                        }
                    ],
                    "MultiplierValue": 3
                },
                {
                    "InputRatingCountPairs": [
                        {
                            "InputRating": "Perfect",
                            "NumberOfInputs": 366
                        },
                        {
                            "InputRating": "Great",
                            "NumberOfInputs": 4
                        }
                    ],
                    "MultiplierValue": 4
                },
                {
                    "InputRatingCountPairs": [
                        {
                            "InputRating": "Perfect",
                            "NumberOfInputs": 89
                        }
                    ],
                    "MultiplierValue": 8
                }
            ],
            "max_combo": 489,
            "pfc": false,
            "player_id": "e8ef8e0a-9976-4fc3-9b8f-3a9a0508cee9",
            "player_name": "Frene",
            "score": 1258671,
            "total_goods": 0,
            "total_greats": 6,
            "total_misses": 0,
            "total_oks": 0,
            "total_perfects": 483,
            "update_epoch": 1770315878274,
            "vibe_chains_hit": 5,
            "vibe_chains_missed": 0,
            "vibe_duration": 25.1322,
            "vibe_times": [
                105.9915,
                161.701,
                288.5784,
                385.6094
            ],
            "vibes": 4
        }
    ],
    "vibe_chains": -1
}